form2request/__init__.py
form2request/_base.py
form2request-0.2.0.dist-info/LICENSE
form2request-0.2.0.dist-info/METADATA
form2request-0.2.0.dist-info/WHEEL
form2request-0.2.0.dist-info/top_level.txt
form2request-0.2.0.dist-info/RECORD
