Metadata-Version: 2.1
Name: form2request
Version: 0.2.0
Summary: Build HTTP requests out of HTML forms
Author-email: Zyte Group Ltd <info@zyte.com>
License: Copyright (c) Zyte Group Ltd
Project-URL: Code, https://github.com/zytedata/form2request
Project-URL: Docs, https://form2request.readthedocs.io/en/latest/
Classifier: Development Status :: 3 - Alpha
Classifier: Intended Audience :: Developers
Classifier: License :: OSI Approved :: BSD License
Classifier: Natural Language :: English
Classifier: Operating System :: OS Independent
Classifier: Programming Language :: Python :: 3
Classifier: Programming Language :: Python :: 3.8
Classifier: Programming Language :: Python :: 3.9
Classifier: Programming Language :: Python :: 3.10
Classifier: Programming Language :: Python :: 3.11
Classifier: Programming Language :: Python :: 3.12
Requires-Python: >=3.8
License-File: LICENSE
Requires-Dist: lxml >=4.4.1
Requires-Dist: parsel >=1.8.1
Requires-Dist: w3lib >=1.19.0
